pynetinstall/__init__.py
pynetinstall/__main__.py
pynetinstall/flash.py
pynetinstall/interface.py
pynetinstall/log.py
pynetinstall/logging.ini
pynetinstall/network.py
pynetinstall/plugins/simple.py
pynetinstall-1.1.0.dist-info/licenses/LICENSE
pynetinstall-1.1.0.dist-info/METADATA
pynetinstall-1.1.0.dist-info/WHEEL
pynetinstall-1.1.0.dist-info/entry_points.txt
pynetinstall-1.1.0.dist-info/top_level.txt
pynetinstall-1.1.0.dist-info/RECORD
